zotman/__init__.py
zotman/cleaner.py
zotman/cli.py
zotman/watcher.py
zotman-0.1.0.dist-info/licenses/LICENSE
zotman-0.1.0.dist-info/METADATA
zotman-0.1.0.dist-info/WHEEL
zotman-0.1.0.dist-info/entry_points.txt
zotman-0.1.0.dist-info/top_level.txt
zotman-0.1.0.dist-info/RECORD
