Metadata-Version: 2.4
Name: zotman
Version: 0.1.0
Summary: Zotero attachment management tools for linked Dropbox workflows
Author-email: Biao Jiang <github@minsignal.com>
License: MIT
Project-URL: Homepage, https://github.com/biaojiang/zotero-tools
Requires-Python: >=3.8
License-File: LICENSE
Requires-Dist: watchdog
Dynamic: license-file
